src/mux.v
module mux #(parameter WIDTH = 5)(
    input wire [WIDTH-1:0] a,
    input wire [WIDTH-1:0] b,
    input wire sel,
    output reg [WIDTH-1:0] out
);

always @(*) begin
    if (sel) begin
        out = b; // If sel is high, output b
    end else begin
        out = a; // If sel is low, output a
    end
end

endmodule

src/alu.v
module alu(
    input wire [31:0] a,
    input wire [31:0] b,
    input wire [5:0] alu_control,
    output reg [31:0] result,
    output reg zero
);

parameter ADD = 6'b100000, SUB = 6'b100010, AND = 6'b100100, OR = 6'b100101,
          SLT = 6'b101010, NOR = 6'b100111, XOR = 6'b100110, SLL = 6'b000000,
          SRL = 6'b000010, SRA = 6'b000011;

always @(*) begin
    case (alu_control)
        ADD: result = a + b;
        SUB: result = a - b;
        AND: result = a & b;
        OR: result = a | b;
        SLT: result = (a < b) ? 1 : 0; // Set on less than
        NOR: result = ~(a | b);
        XOR: result = a ^ b;
        SLL: result = a << b[4:0]; // Shift left logical
        SRL: result = a >> b[4:0]; // Shift right logical
        SRA: result = $signed(a) >>> b[4:0]; // Shift right arithmetic
        default: result = 32'b0; // Default case
    endcase

    zero = (result == 32'b0); // Set zero flag if result is zero
end

endmodule

sim/alu_tb.v
`timescale 1ps/1ps
`define HALFT 5
`include "src/alu.v"
`include "src/mux.v"

module alu_tb();

reg [31:0] a, b;
reg [5:0] alu_control;
reg sel;
wire zero;
wire [31:0] result, result_mux;
alu dut(
    .a(a),
    .b(b),
    .alu_control(alu_control), // ADD operation
    .result(result),
    .zero(zero)
);

mux #(.WIDTH(32)) mux_inst (
    .a(a),
    .b(b),
    .sel(sel),
    .out(result_mux) // Using mux to select result based on zero flag
);

reg clk = 1;
always #(`HALFT) clk = ~clk;

initial begin
    $dumpfile("alu_tb.vcd");
    $dumpvars(0, alu_tb);
end

initial begin
    #(`HALFT * 2);
    // Test ADD operation
    a = 32'h00000001; // Operand A
    b = 32'h00000002; // Operand B
    alu_control = 6'b100000; // ADD operation
    #(`HALFT * 2);
    if (result !== 32'h00000003 || zero !== 0) begin
        $display("Test failed: ADD result = %h, zero = %b", result, zero);
    end else begin
        $display("Test passed: ADD result = %h, zero = %b", result, zero);
    end
    // Test SUB operation
    a = 32'h00000005; // Operand A
    b = 32'h00000003; // Operand B
    alu_control = 6'b100010; // SUB operation
    #(`HALFT * 2);
    if (result !== 32'h00000002 || zero !== 0) begin
        $display("Test failed: SUB result = %h, zero = %b", result, zero);
    end else begin
        $display("Test passed: SUB result = %h, zero = %b", result, zero);
    end
    // Test AND operation
    a = 32'h0000000F; // Operand A
    b = 32'h00000003; // Operand B
    alu_control = 6'b100100; // AND operation
    #(`HALFT * 2);
    if (result !== 32'h00000003 || zero !== 0) begin
        $display("Test failed: AND result = %h, zero = %b", result, zero);
    end else begin
        $display("Test passed: AND result = %h, zero = %b", result, zero);
    end
    // Test OR operation
    a = 32'h0000000F; // Operand A
    b = 32'h000000F0; // Operand B
    alu_control = 6'b100101; // OR operation
    #(`HALFT * 2);
    if (result !== 32'h000000FF || zero !== 0) begin
        $display("Test failed: OR result = %h, zero = %b", result, zero);
    end else begin
        $display("Test passed: OR result = %h, zero = %b", result, zero);
    end
    // Test SLT operation
    a = 32'h00000001; // Operand A
    b = 32'h00000002; // Operand B
    alu_control = 6'b101010; // SLT operation
    #(`HALFT * 2);
    if (result !== 32'h00000001 || zero !== 0) begin
        $display("Test failed: SLT result = %h, zero = %b", result, zero);
    end else begin
        $display("Test passed: SLT result = %h, zero = %b", result, zero);
    end
    // Test NOR operation
    a = 32'h0000000F; // Operand A
    b = 32'h000000F0; // Operand B
    alu_control = 6'b100111; // NOR operation
    #(`HALFT * 2);
    if (result !== 32'hFFFFFF00 || zero !== 0) begin
        $display("Test failed: NOR result = %h, zero = %b", result, zero);
    end else begin
        $display("Test passed: NOR result = %h, zero = %b", result, zero);
    end
    // Test XOR operation
    a = 32'h0000000F; // Operand A
    b = 32'h000000F0; // Operand B
    alu_control = 6'b100110; // XOR operation
    #(`HALFT * 2);
    if (result !== 32'h000000FF || zero !== 0) begin
        $display("Test failed: XOR result = %h, zero = %b", result, zero);
    end else begin
        $display("Test passed: XOR result = %h, zero = %b", result, zero);
    end
    // Test SLL operation
    a = 32'h00000001; // Operand A
    b = 32'h00000002; // Operand B (shift amount)
    alu_control = 6'b000000; // SLL operation
    #(`HALFT * 2);
    if (result !== 32'h00000004 || zero !== 0) begin
        $display("Test failed: SLL result = %h, zero = %b", result, zero);
    end else begin
        $display("Test passed: SLL result = %h, zero = %b", result, zero);
    end
    // Test SRL operation
    a = 32'h00000004; // Operand A
    b = 32'h00000002; // Operand B (shift amount)
    alu_control = 6'b000010; // SRL operation
    sel = 0;
    #(`HALFT * 2);
    if (result !== 32'h00000001 || zero !== 0) begin
        $display("Test failed: SRL result = %h, zero = %b", result, zero);
    end else begin
        $display("Test passed: SRL result = %h, zero = %b", result, zero);
    end
    if (result_mux !== a) begin
        $display("Test failed: Mux output = %h, expected = %h", result_mux, a);
    end else begin
        $display("Test passed: Mux output = %h, expected = %h", result_mux, a);
    end
    // Test SRA operation
    a = 32'h80000004; // Operand A (negative number)
    b = 32'h00000002; // Operand B (shift amount)
    alu_control = 6'b000011; // SRA operation
    #(`HALFT * 2);
    if (result !== 32'he0000001 || zero !== 0) begin
        $display("Test failed: SRA result = %h, zero = %b", result, zero);
    end else begin
        $display("Test passed: SRA result = %h, zero = %b", result, zero);
    end
    // Test default case
    a = 32'h00000001; // Operand A
    b = 32'h00000002; // Operand B
    alu_control = 6'b111111; // Invalid operation
    sel = 1;
    #(`HALFT * 2);
    if (result !== 32'b0 || zero !== 1) begin
        $display("Test failed: Default case result = %h, zero = %b", result, zero);
    end else begin
        $display("Test passed: Default case result = %h, zero = %b", result, zero);
    end
    if (result_mux !== b) begin
        $display("Test failed: Mux output = %h, expected = %h", result_mux, b);
    end else begin
        $display("Test passed: Mux output = %h, expected = %h", result_mux, b);
    end
    $finish;
end

endmodule

alu_tb.vcd
$date
	Sun Jun 22 18:15:50 2025
$end
$version
	Icarus Verilog
$end
$timescale
	1ps
$end
$scope module alu_tb $end
$var wire 1 ! zero $end
$var wire 32 " result_mux [31:0] $end
$var wire 32 # result [31:0] $end
$var reg 32 $ a [31:0] $end
$var reg 6 % alu_control [5:0] $end
$var reg 32 & b [31:0] $end
$var reg 1 ' clk $end
$var reg 1 ( sel $end
$scope module dut $end
$var wire 32 ) a [31:0] $end
$var wire 6 * alu_control [5:0] $end
$var wire 32 + b [31:0] $end
$var parameter 6 , ADD $end
$var parameter 6 - AND $end
$var parameter 6 . NOR $end
$var parameter 6 / OR $end
$var parameter 6 0 SLL $end
$var parameter 6 1 SLT $end
$var parameter 6 2 SRA $end
$var parameter 6 3 SRL $end
$var parameter 6 4 SUB $end
$var parameter 6 5 XOR $end
$var reg 32 6 result [31:0] $end
$var reg 1 ! zero $end
$upscope $end
$scope module mux_inst $end
$var wire 32 7 a [31:0] $end
$var wire 32 8 b [31:0] $end
$var wire 1 ( sel $end
$var parameter 32 9 WIDTH $end
$var reg 32 : out [31:0] $end
$upscope $end
$upscope $end
$enddefinitions $end
$comment Show the parameter values. $end
$dumpall
b100000 9
b100110 5
b100010 4
b10 3
b11 2
b101010 1
b0 0
b100101 /
b100111 .
b100100 -
b100000 ,
$end
#0
$dumpvars
bx :
bx 8
bx 7
bx 6
bx +
bx *
bx )
x(
1'
bx &
bx %
bx $
bx #
bx "
x!
$end
#5
0'
#10
0!
b11 #
b11 6
b1 "
b1 :
1'
b100000 %
b100000 *
b10 &
b10 +
b10 8
b1 $
b1 )
b1 7
#15
0'
#20
b10 #
b10 6
b101 "
b101 :
1'
b100010 %
b100010 *
b11 &
b11 +
b11 8
b101 $
b101 )
b101 7
#25
0'
#30
b11 #
b11 6
b1111 "
b1111 :
1'
b100100 %
b100100 *
b1111 $
b1111 )
b1111 7
#35
0'
#40
b11111111 #
b11111111 6
1'
b100101 %
b100101 *
b11110000 &
b11110000 +
b11110000 8
#45
0'
#50
b1 #
b1 6
b1 "
b1 :
1'
b101010 %
b101010 *
b10 &
b10 +
b10 8
b1 $
b1 )
b1 7
#55
0'
#60
b11111111111111111111111100000000 #
b11111111111111111111111100000000 6
b1111 "
b1111 :
1'
b100111 %
b100111 *
b11110000 &
b11110000 +
b11110000 8
b1111 $
b1111 )
b1111 7
#65
0'
#70
b11111111 #
b11111111 6
1'
b100110 %
b100110 *
#75
0'
#80
b100 #
b100 6
b1 "
b1 :
1'
b0 %
b0 *
b10 &
b10 +
b10 8
b1 $
b1 )
b1 7
#85
0'
#90
b1 #
b1 6
b100 "
b100 :
1'
0(
b10 %
b10 *
b100 $
b100 )
b100 7
#95
0'
#100
b11100000000000000000000000000001 #
b11100000000000000000000000000001 6
b10000000000000000000000000000100 "
b10000000000000000000000000000100 :
1'
b11 %
b11 *
b10000000000000000000000000000100 $
b10000000000000000000000000000100 )
b10000000000000000000000000000100 7
#105
0'
#110
1!
b0 #
b0 6
b10 "
b10 :
1'
1(
b111111 %
b111111 *
b1 $
b1 )
b1 7
